Metadata-Version: 1.0
Name: kafka-cli
Version: 1.1
Summary:  Kafka CLI utility tool.
Home-page: https://github.com/chenwumail/kafka-cli
Author: jack chen
Author-email: chenwumail@foxmail.com
License: UNKNOWN
Platform: UNKNOWN
